poki/__init__.py
poki/main.py
poki-1.0.dist-info/METADATA
poki-1.0.dist-info/WHEEL
poki-1.0.dist-info/entry_points.txt
poki-1.0.dist-info/top_level.txt
poki-1.0.dist-info/RECORD
