Metadata-Version: 2.1
Name: poki
Version: 1.0
Summary: An advanced tool to manage and kill processes on specific ports
Home-page: https://github.com/avnigashi/poki
Author: Avni Gashi
Author-email: avnig92@gmail.com
Classifier: Programming Language :: Python :: 3
Classifier: License :: OSI Approved :: MIT License
Classifier: Operating System :: OS Independent
Requires-Python: >=3.6
Requires-Dist: psutil
Requires-Dist: typing-extensions
Requires-Dist: tabulate
Requires-Dist: colorama
